magcolloid/__init__.py
magcolloid/parameters.py
magcolloid/simulation.py
magcolloid/support.py
magcolloid/lammps_executables/lmp_mac
magcolloid/lammps_executables/lmp_mingw64-native-mpi.exe
magcolloid/lammps_executables/lmp_mingw64-native.exe
magcolloid/lammps_executables/lmp_mingw64.exe
magcolloid/lammps_executables/lmp_mpi
magcolloid/lammps_executables/lmp_serial
magcolloid/lammps_executables/log.lammps
magcolloid-0.3.8.dist-info/METADATA
magcolloid-0.3.8.dist-info/RECORD
magcolloid-0.3.8.dist-info/WHEEL
magcolloid-0.3.8.dist-info/top_level.txt
